dtPyAppFramework/__init__.py
dtPyAppFramework/_description.txt
dtPyAppFramework/_full_name.txt
dtPyAppFramework/_licence.txt
dtPyAppFramework/_metadata.yaml
dtPyAppFramework/_short_name.txt
dtPyAppFramework/_version.txt
dtPyAppFramework/app_context.py
dtPyAppFramework/application.py
dtPyAppFramework/cloud/__init__.py
dtPyAppFramework/cloud/aws.py
dtPyAppFramework/cloud/azure.py
dtPyAppFramework/cloud/cloud_session.py
dtPyAppFramework/decorators/__init__.py
dtPyAppFramework/logging/__init__.py
dtPyAppFramework/logging/default_logging.py
dtPyAppFramework/misc/__init__.py
dtPyAppFramework/misc/packaging/__init__.py
dtPyAppFramework/misc/yaml/__init__.py
dtPyAppFramework/paths/__init__.py
dtPyAppFramework/process/__init__.py
dtPyAppFramework/process/multiprocessing.py
dtPyAppFramework/process/windows_service.py
dtPyAppFramework/resources/__init__.py
dtPyAppFramework/security/__init__.py
dtPyAppFramework/security/crypto.py
dtPyAppFramework/security/error_handling.py
dtPyAppFramework/security/filesystem.py
dtPyAppFramework/security/validation.py
dtPyAppFramework/settings/__init__.py
dtPyAppFramework/settings/settings_reader.py
dtPyAppFramework/settings/secrets/__init__.py
dtPyAppFramework/settings/secrets/aws_secret_store.py
dtPyAppFramework/settings/secrets/azure_secret_store.py
dtPyAppFramework/settings/secrets/keystore.py
dtPyAppFramework/settings/secrets/local_secret_store.py
dtPyAppFramework/settings/secrets/local_secret_stores_manager.py
dtPyAppFramework/settings/secrets/secret_store.py
dtpyappframework-4.2.1.dist-info/licenses/LICENCE.txt
dtpyappframework-4.2.1.dist-info/METADATA
dtpyappframework-4.2.1.dist-info/WHEEL
dtpyappframework-4.2.1.dist-info/top_level.txt
dtpyappframework-4.2.1.dist-info/RECORD
