Metadata-Version: 2.4
Name: dtPyAppFramework
Version: 4.2.1
Summary: A Python library for common features in application development.
Author-email: Digital-Thought <dev@digital-thought.org>
Maintainer-email: Digital-Thought <dev@digital-thought.org>
License: MIT License
Project-URL: Homepage, https://github.com/Digital-Thought/dtPyAppFramework
Project-URL: Repository, https://github.com/Digital-Thought/dtPyAppFramework
Project-URL: Documentation, https://dtpyappframework.readthedocs.io
Keywords: framework,logging,secrets,settings
Classifier: Development Status :: 5 - Production/Stable
Classifier: Intended Audience :: Developers
Classifier: Natural Language :: English
Classifier: Operating System :: Unix
Classifier: Operating System :: POSIX
Classifier: Operating System :: POSIX :: Linux
Classifier: Operating System :: MacOS
Classifier: Operating System :: Microsoft :: Windows
Classifier: Operating System :: OS Independent
Classifier: Programming Language :: Python :: 3.10
Classifier: Programming Language :: Python :: 3.11
Classifier: Programming Language :: Python :: 3.12
Classifier: License :: OSI Approved :: MIT License
Classifier: Topic :: Security
Classifier: Topic :: Software Development :: Libraries :: Python Modules
Classifier: Topic :: System :: Systems Administration
Classifier: Topic :: Utilities
Requires-Python: >=3.10
License-File: LICENCE.txt
Requires-Dist: PyYaml~=6.0.2
Requires-Dist: colorlog~=6.9.0
Requires-Dist: psutil~=6.1.0
Requires-Dist: pybase64~=1.4.0
Requires-Dist: boto3~=1.35.54
Requires-Dist: cryptography~=44.0.0
Requires-Dist: azure-identity
Requires-Dist: azure-keyvault-secrets
Requires-Dist: pytest-mock
Requires-Dist: pytest-watch
Requires-Dist: pytest~=8.3.3
Requires-Dist: watchdog~=6.0.0
Requires-Dist: azure-core~=1.38.0
Requires-Dist: pywin32; platform_system == "Windows"
Requires-Dist: InquirerPy
Requires-Dist: deprecated
Requires-Dist: filelock~=3.20.3
Dynamic: license-file
